{"name":"Header","type":"header","sections":{"announcement-bar":{"type":"announcement-bar","blocks":{"announcement-bar-0":{"type":"announcement","settings":{"text":"You can have more succinct announcements for mobile.","mobile_text":"","announcement_pages":"","color_scheme":"scheme-3"}},"01f1744f-4bdc-4966-8eb5-a7fdf375e9a5":{"type":"announcement","settings":{"text":"Each announcement could be page specific.","mobile_text":"","announcement_pages":"","color_scheme":"scheme-5"}}},"block_order":["announcement-bar-0","01f1744f-4bdc-4966-8eb5-a7fdf375e9a5"],"disabled":true,"settings":{"text_size":"t5","change_slides_speed":6,"enable_accounts":true,"link_1_icon":"question_mark","link_1_label":"Help","link_1_url":"\/","link_2_icon":"","link_2_label":"","link_2_url":"","enable_country_selector":true,"show_country_filter":false,"enable_language_selector":true,"text_padding":0.8,"show_line_separator":true}},"header":{"type":"header","settings":{"sticky_header_type":"always","drawer_on_desktop":"replace_on_scroll","logo_position":"top-left","center_menu_links":true,"enable_accounts":true,"search":"bar","search_size":"large","logo":"shopify:\/\/shop_images\/Clarke_Black_1.png","logo_width":205,"mobile_logo_width":100,"logo_strap":"","logo_strap_text_size":"t6","mobile_logo_position":"left","menu":"main-menu","text_size":"t4","text_weight":"medium","link_headers_third_level":true,"line_separator":"border-top border-bottom","mega_menu_link_label":"","menu_burger":"","link_headers_second_level":true,"drawer_show_login":true,"secondary_links_threshold":5,"drawer_text_size":"1.6","drawer_icon_1":"leaf","drawer_icon_2":"beer","drawer_icon_3":"banana","drawer_icon_4":"paw_print","drawer_icon_5":"speedometer","drawer_icon_6":"","drawer_icon_7":"","drawer_icon_8":"","drawer_icon_9":"","drawer_icon_10":"","cta_enable":true,"cta_icon":"headset","cta_icon_size":3.4,"cta_heading":"HOW CAN WE HELP?","cta_label":"800-842-5275","cta_url":"","cta_text_size":"t7","custom_icon":"","custom_icon_url":"","custom_icon_label":"Get in touch","color_scheme":"scheme-8","menu_color_scheme":"scheme-9","dropdown_menu_color_scheme":"scheme-2","cta_color_scheme":"scheme-8","search_bar_color_scheme":"scheme-2","enable_country_selector":true,"show_country_filter":false,"enable_language_selector":true,"spacing":1.6,"let_it_snow":false}}},"order":["announcement-bar","header"]}